MANIFEST.in
README.txt
setup.py
smart_date/__init__.py
smart_date/date.py
smart_date/smartfunction.py
smart_date.egg-info/PKG-INFO
smart_date.egg-info/SOURCES.txt
smart_date.egg-info/dependency_links.txt
smart_date.egg-info/top_level.txt
smart_date/test/__init__.py
smart_date/test/data_provider.py
smart_date/test/test_date.py
smart_date/test/test_smartfunction.py