Metadata-Version: 1.1
Name: smart-date
Version: 2.0.3
Summary: Interpreter string into an array of dates. A clever feature of Alexei Klimenko.
Home-page: https://github.com/Ravall/smart_date.git
Author: Valeriy Semenov
Author-email: valery.ravall@gmail.com
License: MIT License
Download-URL: https://github.com/Ravall/smart_date/tarball/master
Platform: UNKNOWN
Classifier: Environment :: Web Environment
Classifier: Intended Audience :: Developers
Classifier: Programming Language :: Python
Requires: python (>= 2.5)
